kkcalc/ASF.json
kkcalc/__init__.py
kkcalc/__main__.py
kkcalc/data.py
kkcalc/kk.py
kkcalc/kk_gui.py
kkcalc/test_kk.py
kkcalc-0.8.4.dist-info/LICENSE.txt
kkcalc-0.8.4.dist-info/METADATA
kkcalc-0.8.4.dist-info/WHEEL
kkcalc-0.8.4.dist-info/top_level.txt
kkcalc-0.8.4.dist-info/RECORD
