Metadata-Version: 2.1
Name: kkcalc
Version: 0.8.4
Summary: A calculator for the Kramers Kronig transform of X-ray spectra
Home-page: https://github.com/benajamin/kkcalc
Author: Benjamin Watts
Author-email: benjamin.watts@gmail.com
Classifier: Programming Language :: Python :: 3
Classifier: License :: OSI Approved :: zlib/libpng License  
Classifier: Topic :: Scientific/Engineering :: Physics
Classifier: Operating System :: OS Independent
License-File: LICENSE.txt
Requires-Dist: numpy
Requires-Dist: scipy
